ghid/build.py
ghid/__init__.py
ghid/_ghid.cpython-311-darwin.so
ghid/go.py
ghid/ghid.py
ghid/.dylibs/Python
ghid-0.0.2.dist-info/RECORD
ghid-0.0.2.dist-info/LICENSE
ghid-0.0.2.dist-info/WHEEL
ghid-0.0.2.dist-info/top_level.txt
ghid-0.0.2.dist-info/METADATA
