Metadata-Version: 2.1
Name: ghid
Version: 0.0.2
Summary: Python bindings to ghid, decoding and encoding utilities for GitHub GraphQL Node IDs
Home-page: https://github.com/athenianco/ghid
Author: Athenian
Author-email: denys@athenian.co
Classifier: Programming Language :: Python :: 3
Classifier: License :: OSI Approved :: BSD License
Classifier: Operating System :: OS Independent
License-File: LICENSE
